toxopy/AnovaRM_diff.py
toxopy/MannWhitney_U.py
toxopy/PlotPCA.py
toxopy/PlotTurnPoints.py
toxopy/__init__.py
toxopy/analyze_rois.py
toxopy/analyze_turnpoints.py
toxopy/csv_utils.py
toxopy/data_utils.py
toxopy/dlcboxplot.py
toxopy/ffconcat.py
toxopy/ffsync.py
toxopy/improve_dlc_output.py
toxopy/return_sem.py
toxopy/sniff_boxplot.py
toxopy/version.py
toxopy-0.6.4.dist-info/LICENSE
toxopy-0.6.4.dist-info/WHEEL
toxopy-0.6.4.dist-info/METADATA
toxopy-0.6.4.dist-info/RECORD
