Metadata-Version: 2.1
Name: toxopy
Version: 0.6.4
Summary: Object-specific python package to run automated tasks in the Chase Lab.
Home-page: https://github.com/bchaselab/toxopy
License: UNKNOWN
Author: fcatus
Author-email: f.catus@pm.me
Requires-Python: >=3.6
Classifier: License :: OSI Approved :: MIT License
Classifier: Programming Language :: Python :: 3
Requires-Dist: pandas
Requires-Dist: dlcu
Requires-Dist: numpy
Requires-Dist: tqdm
Requires-Dist: scipy
Requires-Dist: matplotlib
Requires-Dist: seaborn
Requires-Dist: rich
Requires-Dist: dirtyR
Requires-Dist: rdp
Requires-Dist: pca
